hexee/__init__.py
hexee-0.0.1.dist-info/METADATA
hexee-0.0.1.dist-info/WHEEL
hexee-0.0.1.dist-info/licenses/LICENSE
hexee-0.0.1.dist-info/RECORD
